README.md
setup.cfg
setup.py
seatfinder/__init__.py
seatfinder/constants.py
seatfinder/data_container.py
seatfinder/seatfinder.py
seatfinder/timeseries_container.py
seatfinder/timeseries_loader.py
seatfinder.egg-info/PKG-INFO
seatfinder.egg-info/SOURCES.txt
seatfinder.egg-info/dependency_links.txt
seatfinder.egg-info/requires.txt
seatfinder.egg-info/top_level.txt