Metadata-Version: 2.1
Name: seatfinder
Version: 1.0.1
Summary: Easy access to the data of the KIT seatfinder. This project is not affiliated in any way with the original author of https://www.seatfinder.de/
Home-page: https://github.com/soerface/py_seatfinder
License: UNKNOWN
Platform: UNKNOWN
